django_extra_tools/__init__.py
django_extra_tools/http.py
django_extra_tools/management.py
django_extra_tools/middleware.py
django_extra_tools/models.py
django_extra_tools/wsgi_request.py
django_extra_tools/db/__init__.py
django_extra_tools/db/models/__init__.py
django_extra_tools/db/models/aggregates.py
django_extra_tools/db/models/timestampable.py
django_extra_tools/db/models/sql/__init__.py
django_extra_tools/db/models/sql/aggregates.py
django_extra_tools/locale/pl/LC_MESSAGES/django.mo
django_extra_tools/locale/pl/LC_MESSAGES/django.po
django_extra_tools/migrations/0001-initial.py
django_extra_tools/migrations/__init__.py
django_extra_tools/monkey/__init__.py
django_extra_tools/monkey/django.py
django_extra_tools/south_migrations/0001_initial.py
django_extra_tools/south_migrations/__init__.py
django_extra_tools/sql/first.sql
django_extra_tools/sql/last.sql
django_extra_tools/sql/median.sql
django_extra_tools/templatetags/__init__.py
django_extra_tools/templatetags/parse.py
django_extra_tools-0.3.0.dist-info/DESCRIPTION.rst
django_extra_tools-0.3.0.dist-info/METADATA
django_extra_tools-0.3.0.dist-info/RECORD
django_extra_tools-0.3.0.dist-info/WHEEL
django_extra_tools-0.3.0.dist-info/metadata.json
django_extra_tools-0.3.0.dist-info/top_level.txt
